ossbomer_conformance/__init__.py
ossbomer_conformance/cli.py
ossbomer_conformance/config.json
ossbomer_conformance/validator.py
ossbomer_conformance-1.3.0.dist-info/LICENSE
ossbomer_conformance-1.3.0.dist-info/METADATA
ossbomer_conformance-1.3.0.dist-info/WHEEL
ossbomer_conformance-1.3.0.dist-info/entry_points.txt
ossbomer_conformance-1.3.0.dist-info/top_level.txt
ossbomer_conformance-1.3.0.dist-info/RECORD
