Metadata-Version: 2.1
Name: ossbomer-conformance
Version: 1.3.0
Summary: OSSBOMER - SBOM Conformance against NTIA, CRA, and other compliance requirements.
Author: Oscar Valenzuela
Author-email: oscar.valenzuela.b@gmail.com
Classifier: License :: OSI Approved :: MIT License
Classifier: Programming Language :: Python :: 3
Requires-Python: >=3.7
License-File: LICENSE
Requires-Dist: click>=8.0
Requires-Dist: jsonschema>=4.0
